skkeras/__init__.py
skkeras/build_fn.py
skkeras/scikit_learn.py
tests/__init__.py
tests/test_build_fn.py
tests/test_scikit_learn.py
scikit_keras-0.2.0.dist-info/LICENSE
scikit_keras-0.2.0.dist-info/METADATA
scikit_keras-0.2.0.dist-info/WHEEL
scikit_keras-0.2.0.dist-info/top_level.txt
scikit_keras-0.2.0.dist-info/RECORD
