Metadata-Version: 2.1
Name: scikit-keras
Version: 0.2.0
Summary: Scikit-learn-compatible Keras models
Home-page: https://github.com/daviddiazvico/scikit-keras
Download-URL: https://github.com/daviddiazvico/scikit-keras/archive/v0.2.0.tar.gz
Author: David Diaz Vico
Author-email: david.diaz.vico@outlook.com
License: UNKNOWN
Keywords: scikit-learn,keras
Platform: UNKNOWN
Classifier: Intended Audience :: Science/Research
Classifier: Intended Audience :: Developers
Classifier: Topic :: Software Development
Classifier: Topic :: Scientific/Engineering
Classifier: Programming Language :: Python
Classifier: Programming Language :: Python :: 3
Classifier: Programming Language :: Python :: 3.7
Classifier: Programming Language :: Python :: 3.8
Classifier: Programming Language :: Python :: 3.9
Classifier: Programming Language :: Python :: 3.10
License-File: LICENSE
Requires-Dist: scikit-learn
Requires-Dist: tensorflow
